tartiflette_middleware/__init__.py
tartiflette_middleware/base_middleware.py
tartiflette_middleware/middleware.py
tartiflette_middleware/exceptions/__init__.py
tartiflette_middleware/exceptions/exceptions.py
tartiflette_middleware/server/__init__.py
tartiflette_middleware/server/aiohttp.py
tartiflette_middleware-1.1.dist-info/LICENSE
tartiflette_middleware-1.1.dist-info/METADATA
tartiflette_middleware-1.1.dist-info/WHEEL
tartiflette_middleware-1.1.dist-info/top_level.txt
tartiflette_middleware-1.1.dist-info/RECORD
