Metadata-Version: 2.1
Name: tartiflette-middleware
Version: 1.1
Summary: Framework for middleware for Tartiflette, with context data assignment
Home-page: https://github.com/daveoconnor/tartiflette-middleware
Author: Dave O'Connor
Author-email: github@dead-pixels.org
License: UNKNOWN
Platform: UNKNOWN
Classifier: Programming Language :: Python :: 3
Classifier: License :: OSI Approved :: MIT License
Classifier: Operating System :: OS Independent
Requires-Python: >=3.8
Requires-Dist: tartiflette (>=1.2)
